fei_cpp_library/__init__.py
fei_cpp_library/other_module.py
fei_cpp_library-0.1.3.dist-info/licenses/LICENSE
fei_cpp_library-0.1.3.dist-info/METADATA
fei_cpp_library-0.1.3.dist-info/WHEEL
fei_cpp_library-0.1.3.dist-info/top_level.txt
fei_cpp_library-0.1.3.dist-info/RECORD
